docs_tc.py
evaluate_coverage.py
extract_data_from_markdown.py
generate_embeddings.py
generate_report.py
generate_report_html.py
limpa_csv.py
merge_markdown.py
docs_cli_toolkit-0.1.3.dist-info/licenses/LICENSE
docs_cli_toolkit-0.1.3.dist-info/METADATA
docs_cli_toolkit-0.1.3.dist-info/WHEEL
docs_cli_toolkit-0.1.3.dist-info/entry_points.txt
docs_cli_toolkit-0.1.3.dist-info/top_level.txt
docs_cli_toolkit-0.1.3.dist-info/RECORD
