Metadata-Version: 2.4
Name: docs-cli-toolkit
Version: 0.1.3
Summary: Um toolkit para processamento e avaliação de documentação, com suporte a geração de embeddings usando a API do Google Gemini.
Author-email: Paulo Guilherme Pilott <paulo@paulogpd.com.br>
License: MIT
Project-URL: Homepage, https://github.com/seu-usuario/docs-cli-toolkit
Project-URL: Repository, https://github.com/seu-usuario/docs-cli-toolkit.git
Project-URL: Issues, https://github.com/seu-usuario/docs-cli-toolkit/issues
Classifier: Programming Language :: Python :: 3
Classifier: Operating System :: OS Independent
Classifier: Development Status :: 3 - Alpha
Classifier: Intended Audience :: Developers
Classifier: Topic :: Documentation
Classifier: Topic :: Utilities
Classifier: Environment :: Console
Classifier: Programming Language :: Python :: 3.8
Classifier: Programming Language :: Python :: 3.9
Classifier: Programming Language :: Python :: 3.10
Classifier: Programming Language :: Python :: 3.11
Requires-Python: >=3.8
License-File: LICENSE
Requires-Dist: google-generativeai>=0.3.0
Requires-Dist: python-dotenv>=1.0.0
Requires-Dist: numpy>=1.24.0
Requires-Dist: pandas>=2.0.0
Requires-Dist: requests>=2.31.0
Requires-Dist: openai>=1.0.0
Dynamic: license-file
